Users/babbage/surfing.conf.example.json
cli/__init__.py
cli/entry.py
cli/devops/__init__.py
cli/devops/ftpserver_helper.py
cli/devops/controllers/__init__.py
cli/devops/controllers/ftpserver_helper_controller.py
cli/devops/py_configs/__init__.py
cli/devops/py_configs/ftp_server_config.py
cli/packages/__init__.py
cli/packages/assistant.py
cli/packages/compare_file.py
cli/packages/convert_utf8.py
cli/packages/fix_wrong_packagename_files.py
cli/packages/is_src_exist_on_dest.py
cli/packages/read_metadata_file.py
cli/packages/remove_bom.py
cli/packages/controllers/__init__.py
cli/packages/controllers/package_analysis_controller.py
cli/packages/utils/__init__.py
cli/packages/utils/decrypt_audio.py
cli/packages/utils/remove_utf8_bom.py
cli/send_mail/__init__.py
cli/send_mail/send_mail.py
cli/send_mail/controller/__init__.py
cli/send_mail/controller/send_mail_controller.py
configs/Config.py
configs/__init__.py
models/__init__.py
models/package_model.py
surfing_cli-2.6.8.dist-info/METADATA
surfing_cli-2.6.8.dist-info/WHEEL
surfing_cli-2.6.8.dist-info/entry_points.txt
surfing_cli-2.6.8.dist-info/top_level.txt
surfing_cli-2.6.8.dist-info/RECORD
