Metadata-Version: 2.1
Name: surfing-cli
Version: 2.6.8
Summary: 冲浪科技专用脚本库
Home-page: https://github.com/uighurbabbage
Author: Babbage
Author-email: babbage@hotmail.com
License: UNKNOWN
Platform: UNKNOWN
Classifier: Programming Language :: Python :: 3
Classifier: License :: OSI Approved :: MIT License
Classifier: Operating System :: OS Independent
Requires-Dist: Click
Requires-Dist: xlwt
Requires-Dist: pycrypto
Requires-Dist: chardet
Requires-Dist: fabric
